keygen_python_sdk/__init__.py
keygen_python_sdk/config.py
keygen_python_sdk/exceptions.py
keygen_python_sdk/functional.py
keygen_python_sdk/models.py
keygen_python_sdk/py.typed
keygen_python_sdk-0.3.1.dist-info/METADATA
keygen_python_sdk-0.3.1.dist-info/WHEEL
keygen_python_sdk-0.3.1.dist-info/licenses/LICENSE
keygen_python_sdk-0.3.1.dist-info/RECORD
