Metadata-Version: 2.4
Name: keygen-python-sdk
Version: 0.3.1
Summary: Keygen Python SDK
Project-URL: Homepage, https://pypi.org/p/keygen-python-sdk
Project-URL: Docs, https://keygen-python-sdk.readthedocs.io/en/latest/index.html
Project-URL: Source, https://github.com/massarom/keygen-python-sdk
Project-URL: Issues, https://github.com/massarom/keygen-python-sdk/issues
Author-email: Marcello Massaro <18736562+massarom@users.noreply.github.com>
License: 
License-File: LICENSE
Keywords: keygen-sh,licensing
Classifier: Development Status :: 3 - Alpha
Classifier: Framework :: Pydantic
Classifier: Intended Audience :: Developers
Classifier: License :: OSI Approved :: Apache Software License
Classifier: Operating System :: OS Independent
Classifier: Typing :: Typed
Requires-Python: >=3.10
Requires-Dist: py-machineid>=0.6.0
Requires-Dist: pydantic-settings>=2.6.1
Requires-Dist: pydantic>=2.10.3
Requires-Dist: pynacl>=1.5.0
Requires-Dist: requests>=2.32.3
